LICENCE.txt
MANIFEST.in
README.md
ez_setup.py
setup.py
runm/__init__.py
runm.egg-info/PKG-INFO
runm.egg-info/SOURCES.txt
runm.egg-info/dependency_links.txt
runm.egg-info/top_level.txt
test/test_runm.py