Metadata-Version: 1.0
Name: runm
Version: 0.0.2
Summary: UNKNOWN
Home-page: UNKNOWN
Author: Ben Woodcroft
Author-email: donttrustben@gmail.com
License: MIT
Platform: UNKNOWN
